[
    {
        "rank": "1.",
        "name": "Anthony Modeste",
        "country": "France",
        "team": "1. FC Köln",
        "goals": "8",
        "flag": "france",
        "logo": "1__fc_koln"
    },
    {
        "rank": "2.",
        "name": "Pierre-Emerick Aubameyang",
        "country": "Gabon",
        "team": "Borussia Dortmund",
        "goals": "7",
        "flag": "gabon",
        "logo": "borussia_dortmund"
    },
    {
        "rank": "3.",
        "name": "Vedad Ibišević",
        "country": "Bosnia-Herzegovina",
        "team": "Hertha BSC",
        "goals": "6",
        "flag": "bosnia_herzegovina",
        "logo": "hertha_bsc"
    },
    {
        "rank": "4.",
        "name": "Javier Hernández",
        "country": "Mexico",
        "team": "Bayer Leverkusen",
        "goals": "5",
        "flag": "mexico",
        "logo": "bayer_leverkusen"
    },
    {
        "rank": "-",
        "name": "Robert Lewandowski",
        "country": "Poland",
        "team": "Bayern München",
        "goals": "5",
        "flag": "poland",
        "logo": "bayern_munchen"
    },
    {
        "rank": "6.",
        "name": "Pablo de Blasis",
        "country": "Argentina",
        "team": "1. FSV Mainz 05",
        "goals": "4",
        "flag": "argentina",
        "logo": "1__fsv_mainz_05"
    },
    {
        "rank": "-",
        "name": "Joshua Kimmich",
        "country": "Germany",
        "team": "Bayern München",
        "goals": "4",
        "flag": "germany",
        "logo": "bayern_munchen"
    },
    {
        "rank": "-",
        "name": "Yunus Mallı",
        "country": "Turkey",
        "team": "1. FSV Mainz 05",
        "goals": "4",
        "flag": "turkey",
        "logo": "1__fsv_mainz_05"
    },
    {
        "rank": "-",
        "name": "Maximilian Philipp",
        "country": "Germany",
        "team": "SC Freiburg",
        "goals": "4",
        "flag": "germany",
        "logo": "sc_freiburg"
    },
    {
        "rank": "-",
        "name": "Joel Pohjanpalo",
        "country": "Finland",
        "team": "Bayer Leverkusen",
        "goals": "4",
        "flag": "finland",
        "logo": "bayer_leverkusen"
    },
    {
        "rank": "-",
        "name": "Sandro Wagner",
        "country": "Germany",
        "team": "1899 Hoffenheim",
        "goals": "4",
        "flag": "germany",
        "logo": "1899_hoffenheim"
    },
    {
        "rank": "12.",
        "name": "Nabil Bentaleb",
        "country": "Algeria",
        "team": "FC Schalke 04",
        "goals": "3",
        "flag": "algeria",
        "logo": "fc_schalke_04"
    },
    {
        "rank": "-",
        "name": "Marco Fabián",
        "country": "Mexico",
        "team": "Eintracht Frankfurt",
        "goals": "3",
        "flag": "mexico",
        "logo": "eintracht_frankfurt"
    },
    {
        "rank": "-",
        "name": "Emil Forsberg",
        "country": "Sweden",
        "team": "RB Leipzig",
        "goals": "3",
        "flag": "sweden",
        "logo": "rb_leipzig"
    },
    {
        "rank": "-",
        "name": "Serge Gnabry",
        "country": "Germany",
        "team": "Werder Bremen",
        "goals": "3",
        "flag": "germany",
        "logo": "werder_bremen"
    },
    {
        "rank": "-",
        "name": "Thorgan Hazard",
        "country": "Belgium",
        "team": "Bor. Mönchengladbach",
        "goals": "3",
        "flag": "belgium",
        "logo": "bor__monchengladbach"
    },
    {
        "rank": "-",
        "name": "Lukas Hinterseer",
        "country": "Austria",
        "team": "FC Ingolstadt 04",
        "goals": "3",
        "flag": "austria",
        "logo": "fc_ingolstadt_04"
    },
    {
        "rank": "-",
        "name": "Naby Keita",
        "country": "Guinea",
        "team": "RB Leipzig",
        "goals": "3",
        "flag": "guinea",
        "logo": "rb_leipzig"
    },
    {
        "rank": "-",
        "name": "Andrej Kramarić",
        "country": "Croatia",
        "team": "1899 Hoffenheim",
        "goals": "3",
        "flag": "croatia",
        "logo": "1899_hoffenheim"
    },
    {
        "rank": "-",
        "name": "Dario Lezcano",
        "country": "Paraguay",
        "team": "FC Ingolstadt 04",
        "goals": "3",
        "flag": "paraguay",
        "logo": "fc_ingolstadt_04"
    }
]