[
    {
        "rank": "1",
        "team": "FC Barcelona",
        "points": "54",
        "played": "24",
        "win": "16",
        "draw": "6",
        "lost": "2",
        "goalsFor": "61",
        "goalsAgainst": "23",
        "goalDifference": "38",
        "logo": "fc_barcelona"
    },
    {
        "rank": "2",
        "team": "Atlético Madrid",
        "points": "47",
        "played": "24",
        "win": "13",
        "draw": "8",
        "lost": "3",
        "goalsFor": "34",
        "goalsAgainst": "17",
        "goalDifference": "17",
        "logo": "atletico_madrid"
    },
    {
        "rank": "3",
        "team": "Real Madrid",
        "points": "45",
        "played": "24",
        "win": "14",
        "draw": "3",
        "lost": "7",
        "goalsFor": "41",
        "goalsAgainst": "29",
        "goalDifference": "12",
        "logo": "real_madrid"
    },
    {
        "rank": "4",
        "team": "Sevilla FC",
        "points": "37",
        "played": "24",
        "win": "10",
        "draw": "7",
        "lost": "7",
        "goalsFor": "38",
        "goalsAgainst": "28",
        "goalDifference": "10",
        "logo": "sevilla_fc"
    },
    {
        "rank": "5",
        "team": "Getafe CF",
        "points": "36",
        "played": "24",
        "win": "9",
        "draw": "9",
        "lost": "6",
        "goalsFor": "30",
        "goalsAgainst": "21",
        "goalDifference": "9",
        "logo": "getafe_cf"
    },
    {
        "rank": "6",
        "team": "CD Alavés",
        "points": "36",
        "played": "24",
        "win": "10",
        "draw": "6",
        "lost": "8",
        "goalsFor": "25",
        "goalsAgainst": "28",
        "goalDifference": "-3",
        "logo": "cd_alaves"
    },
    {
        "rank": "7",
        "team": "Real Sociedad",
        "points": "34",
        "played": "24",
        "win": "9",
        "draw": "7",
        "lost": "8",
        "goalsFor": "30",
        "goalsAgainst": "25",
        "goalDifference": "5",
        "logo": "real_sociedad"
    },
    {
        "rank": "8",
        "team": "Real Betis",
        "points": "33",
        "played": "24",
        "win": "9",
        "draw": "6",
        "lost": "9",
        "goalsFor": "27",
        "goalsAgainst": "30",
        "goalDifference": "-3",
        "logo": "real_betis"
    },
    {
        "rank": "9",
        "team": "Valencia CF",
        "points": "32",
        "played": "24",
        "win": "6",
        "draw": "14",
        "lost": "4",
        "goalsFor": "24",
        "goalsAgainst": "20",
        "goalDifference": "4",
        "logo": "valencia_cf"
    },
    {
        "rank": "10",
        "team": "SD Eibar",
        "points": "31",
        "played": "24",
        "win": "7",
        "draw": "10",
        "lost": "7",
        "goalsFor": "33",
        "goalsAgainst": "34",
        "goalDifference": "-1",
        "logo": "sd_eibar"
    },
    {
        "rank": "11",
        "team": "Levante UD",
        "points": "30",
        "played": "24",
        "win": "8",
        "draw": "6",
        "lost": "10",
        "goalsFor": "36",
        "goalsAgainst": "43",
        "goalDifference": "-7",
        "logo": "levante_ud"
    },
    {
        "rank": "12",
        "team": "CD Leganés",
        "points": "29",
        "played": "24",
        "win": "7",
        "draw": "8",
        "lost": "9",
        "goalsFor": "25",
        "goalsAgainst": "30",
        "goalDifference": "-5",
        "logo": "cd_leganes"
    },
    {
        "rank": "13",
        "team": "Espanyol Barcelona",
        "points": "29",
        "played": "24",
        "win": "8",
        "draw": "5",
        "lost": "11",
        "goalsFor": "27",
        "goalsAgainst": "37",
        "goalDifference": "-10",
        "logo": "espanyol_barcelona"
    },
    {
        "rank": "14",
        "team": "Athletic Bilbao",
        "points": "27",
        "played": "23",
        "win": "5",
        "draw": "12",
        "lost": "6",
        "goalsFor": "23",
        "goalsAgainst": "28",
        "goalDifference": "-5",
        "logo": "athletic_bilbao"
    },
    {
        "rank": "15",
        "team": "Girona FC",
        "points": "27",
        "played": "24",
        "win": "6",
        "draw": "9",
        "lost": "9",
        "goalsFor": "25",
        "goalsAgainst": "34",
        "goalDifference": "-9",
        "logo": "girona_fc"
    },
    {
        "rank": "16",
        "team": "Real Valladolid",
        "points": "26",
        "played": "24",
        "win": "6",
        "draw": "8",
        "lost": "10",
        "goalsFor": "19",
        "goalsAgainst": "29",
        "goalDifference": "-10",
        "logo": "real_valladolid"
    },
    {
        "rank": "17",
        "team": "Celta Vigo",
        "points": "24",
        "played": "24",
        "win": "6",
        "draw": "6",
        "lost": "12",
        "goalsFor": "36",
        "goalsAgainst": "43",
        "goalDifference": "-7",
        "logo": "celta_vigo"
    },
    {
        "rank": "18",
        "team": "Villarreal CF",
        "points": "23",
        "played": "24",
        "win": "4",
        "draw": "11",
        "lost": "9",
        "goalsFor": "26",
        "goalsAgainst": "31",
        "goalDifference": "-5",
        "logo": "villarreal_cf"
    },
    {
        "rank": "19",
        "team": "Rayo Vallecano",
        "points": "23",
        "played": "24",
        "win": "6",
        "draw": "5",
        "lost": "13",
        "goalsFor": "27",
        "goalsAgainst": "41",
        "goalDifference": "-14",
        "logo": "rayo_vallecano"
    },
    {
        "rank": "20",
        "team": "SD Huesca",
        "points": "18",
        "played": "23",
        "win": "4",
        "draw": "6",
        "lost": "13",
        "goalsFor": "23",
        "goalsAgainst": "39",
        "goalDifference": "-16",
        "logo": "sd_huesca"
    }
]