[
    {
        "rank": "1",
        "team": "Manchester City",
        "points": "20",
        "played": "9",
        "win": "6",
        "draw": "2",
        "lost": "1",
        "goalsFor": "20",
        "goalsAgainst": "9",
        "goalDifference": "11",
        "logo": "manchester_city"
    },
    {
        "rank": "2",
        "team": "Arsenal FC",
        "points": "20",
        "played": "9",
        "win": "6",
        "draw": "2",
        "lost": "1",
        "goalsFor": "19",
        "goalsAgainst": "9",
        "goalDifference": "10",
        "logo": "arsenal_fc"
    },
    {
        "rank": "3",
        "team": "Liverpool FC",
        "points": "20",
        "played": "9",
        "win": "6",
        "draw": "2",
        "lost": "1",
        "goalsFor": "20",
        "goalsAgainst": "11",
        "goalDifference": "9",
        "logo": "liverpool_fc"
    },
    {
        "rank": "4",
        "team": "Chelsea FC",
        "points": "19",
        "played": "9",
        "win": "6",
        "draw": "1",
        "lost": "2",
        "goalsFor": "19",
        "goalsAgainst": "9",
        "goalDifference": "10",
        "logo": "chelsea_fc"
    },
    {
        "rank": "5",
        "team": "Tottenham Hotspur",
        "points": "19",
        "played": "9",
        "win": "5",
        "draw": "4",
        "lost": "0",
        "goalsFor": "13",
        "goalsAgainst": "4",
        "goalDifference": "9",
        "logo": "tottenham_hotspur"
    },
    {
        "rank": "6",
        "team": "Everton FC",
        "points": "15",
        "played": "9",
        "win": "4",
        "draw": "3",
        "lost": "2",
        "goalsFor": "13",
        "goalsAgainst": "8",
        "goalDifference": "5",
        "logo": "everton_fc"
    },
    {
        "rank": "7",
        "team": "Manchester United",
        "points": "14",
        "played": "9",
        "win": "4",
        "draw": "2",
        "lost": "3",
        "goalsFor": "13",
        "goalsAgainst": "12",
        "goalDifference": "1",
        "logo": "manchester_united"
    },
    {
        "rank": "8",
        "team": "Southampton FC",
        "points": "13",
        "played": "9",
        "win": "3",
        "draw": "4",
        "lost": "2",
        "goalsFor": "11",
        "goalsAgainst": "8",
        "goalDifference": "3",
        "logo": "southampton_fc"
    },
    {
        "rank": "9",
        "team": "Watford FC",
        "points": "12",
        "played": "9",
        "win": "3",
        "draw": "3",
        "lost": "3",
        "goalsFor": "13",
        "goalsAgainst": "13",
        "goalDifference": "0",
        "logo": "watford_fc"
    },
    {
        "rank": "10",
        "team": "AFC Bournemouth",
        "points": "12",
        "played": "9",
        "win": "3",
        "draw": "3",
        "lost": "3",
        "goalsFor": "12",
        "goalsAgainst": "12",
        "goalDifference": "0",
        "logo": "afc_bournemouth"
    },
    {
        "rank": "11",
        "team": "Crystal Palace",
        "points": "11",
        "played": "9",
        "win": "3",
        "draw": "2",
        "lost": "4",
        "goalsFor": "12",
        "goalsAgainst": "12",
        "goalDifference": "0",
        "logo": "crystal_palace"
    },
    {
        "rank": "12",
        "team": "Leicester City",
        "points": "11",
        "played": "9",
        "win": "3",
        "draw": "2",
        "lost": "4",
        "goalsFor": "11",
        "goalsAgainst": "15",
        "goalDifference": "-4",
        "logo": "leicester_city"
    },
    {
        "rank": "13",
        "team": "West Bromwich Albion",
        "points": "10",
        "played": "9",
        "win": "2",
        "draw": "4",
        "lost": "3",
        "goalsFor": "10",
        "goalsAgainst": "10",
        "goalDifference": "0",
        "logo": "west_bromwich_albion"
    },
    {
        "rank": "14",
        "team": "Burnley FC",
        "points": "10",
        "played": "9",
        "win": "3",
        "draw": "1",
        "lost": "5",
        "goalsFor": "8",
        "goalsAgainst": "13",
        "goalDifference": "-5",
        "logo": "burnley_fc"
    },
    {
        "rank": "15",
        "team": "West Ham United",
        "points": "10",
        "played": "9",
        "win": "3",
        "draw": "1",
        "lost": "5",
        "goalsFor": "10",
        "goalsAgainst": "17",
        "goalDifference": "-7",
        "logo": "west_ham_united"
    },
    {
        "rank": "16",
        "team": "Stoke City",
        "points": "9",
        "played": "9",
        "win": "2",
        "draw": "3",
        "lost": "4",
        "goalsFor": "9",
        "goalsAgainst": "16",
        "goalDifference": "-7",
        "logo": "stoke_city"
    },
    {
        "rank": "17",
        "team": "Middlesbrough FC",
        "points": "7",
        "played": "9",
        "win": "1",
        "draw": "4",
        "lost": "4",
        "goalsFor": "7",
        "goalsAgainst": "11",
        "goalDifference": "-4",
        "logo": "middlesbrough_fc"
    },
    {
        "rank": "18",
        "team": "Hull City",
        "points": "7",
        "played": "9",
        "win": "2",
        "draw": "1",
        "lost": "6",
        "goalsFor": "8",
        "goalsAgainst": "22",
        "goalDifference": "-14",
        "logo": "hull_city"
    },
    {
        "rank": "19",
        "team": "Swansea City",
        "points": "5",
        "played": "9",
        "win": "1",
        "draw": "2",
        "lost": "6",
        "goalsFor": "8",
        "goalsAgainst": "15",
        "goalDifference": "-7",
        "logo": "swansea_city"
    },
    {
        "rank": "20",
        "team": "Sunderland AFC",
        "points": "2",
        "played": "9",
        "win": "0",
        "draw": "2",
        "lost": "7",
        "goalsFor": "6",
        "goalsAgainst": "16",
        "goalDifference": "-10",
        "logo": "sunderland_afc"
    }
]