[{"rank":"1","name":"","team":"","goals":"","played":"19280.68"},{"rank":"2","name":"","team":"","goals":"","played":"17270.63"},{"rank":"3","name":"","team":"","goals":"","played":"16270.59"},{"rank":"4","name":"","team":"","goals":"","played":"15270.56"},{"rank":"5","name":"","team":"","goals":"","played":"14270.52"},{"rank":"-","name":"","team":"","goals":"","played":"14190.74"},{"rank":"7","name":"","team":"","goals":"","played":"12270.44"},{"rank":"8","name":"","team":"","goals":"","played":"11240.46"},{"rank":"9","name":"","team":"","goals":"","played":"10240.42"},{"rank":"10","name":"","team":"","goals":"","played":"9260.35"},{"rank":"-","name":"","team":"","goals":"","played":"9240.38"},{"rank":"12","name":"","team":"","goals":"","played":"8270.30"},{"rank":"-","name":"","team":"","goals":"","played":"8260.31"},{"rank":"-","name":"","team":"","goals":"","played":"8270.30"},{"rank":"15","name":"","team":"","goals":"","played":"7210.33"},{"rank":"-","name":"","team":"","goals":"","played":"7220.32"},{"rank":"-","name":"","team":"","goals":"","played":"7200.35"},{"rank":"-","name":"","team":"","goals":"","played":"7270.26"},{"rank":"-","name":"","team":"","goals":"","played":"7250.28"},{"rank":"-","name":"","team":"","goals":"","played":"7200.35"}]