[
    {
        "rank": "1.",
        "name": "James Rodríguez",
        "country": "Colombia",
        "team": "AS Monaco",
        "goals": "12"
    },
    {
        "rank": "2.",
        "name": "Zlatan Ibrahimović",
        "country": "Sweden",
        "team": "Paris Saint-Germain",
        "goals": "11"
    },
    {
        "rank": "3.",
        "name": " Lucas",
        "country": "Brazil",
        "team": "Paris Saint-Germain",
        "goals": "9"
    },
    {
        "rank": "-",
        "name": "Grégory Sertić",
        "country": "France",
        "team": "Girondins Bordeaux",
        "goals": "9"
    },
    {
        "rank": "5.",
        "name": "Henri Bédimo",
        "country": "Cameroon",
        "team": "Olympique Lyon",
        "goals": "8"
    },
    {
        "rank": "6.",
        "name": " João Moutinho",
        "country": "Portugal",
        "team": "AS Monaco",
        "goals": "7"
    },
    {
        "rank": "-",
        "name": "Mathieu Valbuena",
        "country": "France",
        "team": "Olympique Marseille",
        "goals": "7"
    },
    {
        "rank": "8.",
        "name": "Vincent Aboubakar",
        "country": "Cameroon",
        "team": "FC Lorient",
        "goals": "6"
    },
    {
        "rank": "-",
        "name": "Serge Aurier",
        "country": "Ivory Coast",
        "team": "Toulouse FC",
        "goals": "6"
    },
    {
        "rank": "-",
        "name": "Florent Balmont",
        "country": "France",
        "team": "Lille OSC",
        "goals": "6"
    },
    {
        "rank": "-",
        "name": "Cédric Barbosa",
        "country": "France",
        "team": "Évian Thonon Gaillard",
        "goals": "6"
    },
    {
        "rank": "-",
        "name": "Ryad Boudebouz",
        "country": "Algeria",
        "team": "FC Sochaux",
        "goals": "6"
    },
    {
        "rank": "-",
        "name": "Martin Braithwaite",
        "country": "Denmark",
        "team": "Toulouse FC",
        "goals": "6"
    },
    {
        "rank": "-",
        "name": "Johan Cavalli",
        "country": "France",
        "team": "AC Ajaccio",
        "goals": "6"
    },
    {
        "rank": "-",
        "name": "Yann Jouffre",
        "country": "France",
        "team": "FC Lorient",
        "goals": "6"
    },
    {
        "rank": "16.",
        "name": "Romain Alessandrini",
        "country": "France",
        "team": "Stade Rennes",
        "goals": "5"
    },
    {
        "rank": "-",
        "name": "Benjamin André",
        "country": "France",
        "team": "AC Ajaccio",
        "goals": "5"
    },
    {
        "rank": "-",
        "name": "Wissam Ben Yedder",
        "country": "France",
        "team": "Toulouse FC",
        "goals": "5"
    },
    {
        "rank": "-",
        "name": "Jimmy Briand",
        "country": "France",
        "team": "Olympique Lyon",
        "goals": "5"
    },
    {
        "rank": "-",
        "name": "Christian Brüls",
        "country": "Belgium",
        "team": "OGC Nice",
        "goals": "5"
    }
]