[{"rank":"1 ","name":"Luis Suárez","team":"Barcelona","goals":"10"},{"rank":"2 ","name":"Neymar","team":"Barcelona","goals":"9"},{"rank":"3 ","name":"Toni Kroos","team":"Real Madrid","goals":"8"},{"rank":"-","name":"Cristiano Ronaldo","team":"Real Madrid","goals":"8"},{"rank":"-","name":"Roberto Soldado","team":"Villarreal","goals":"8"},{"rank":"-","name":"Gareth Bale","team":"Real Madrid","goals":"8"},{"rank":"7 ","name":"Lionel Messi","team":"Barcelona","goals":"7"},{"rank":"-","name":"Rubén Pardo","team":"Real Sociedad","goals":"7"},{"rank":"-","name":"Koke","team":"Atletico Madrid","goals":"7"},{"rank":"10 ","name":"James Rodríguez","team":"Real Madrid","goals":"6"},{"rank":"-","name":"Lucas","team":"Deportivo La Coruña","goals":"6"},{"rank":"-","name":"Marco Asensio","team":"Espanyol","goals":"6"},{"rank":"-","name":"Sergi Enrich","team":"Eibar","goals":"6"},{"rank":"14 ","name":"Alen Halilovic","team":"Sporting Gijón","goals":"5"},{"rank":"-","name":"Roberto Trashorras","team":"Rayo Vallecano","goals":"5"},{"rank":"-","name":"Ruben Rochina","team":"Granada","goals":"5"},{"rank":"-","name":"Daniel Wass","team":"Celta Vigo","goals":"5"},{"rank":"-","name":"Nolito","team":"Celta Vigo","goals":"5"},{"rank":"-","name":"Paco Alcacer","team":"Valencia","goals":"5"},{"rank":"20 ","name":"Luis Alberto","team":"Deportivo La Coruña","goals":"4"}]