[
    {
        "rank": "1.",
        "name": "Ruud van Nistelrooy",
        "country": "Netherlands",
        "team": "Manchester United",
        "goals": "25",
        "flag": "netherlands",
        "logo": "manchester_united"
    },
    {
        "rank": "2.",
        "name": "Thierry Henry",
        "country": "France",
        "team": "Arsenal FC",
        "goals": "24",
        "flag": "france",
        "logo": "arsenal_fc"
    },
    {
        "rank": "3.",
        "name": "James Beattie",
        "country": "England",
        "team": "Southampton FC",
        "goals": "23",
        "flag": "england",
        "logo": "southampton_fc"
    },
    {
        "rank": "4.",
        "name": "Mark Viduka",
        "country": "Australia",
        "team": "Leeds United",
        "goals": "20",
        "flag": "australia",
        "logo": "leeds_united"
    },
    {
        "rank": "5.",
        "name": "Michael Owen",
        "country": "England",
        "team": "Liverpool FC",
        "goals": "19",
        "flag": "england",
        "logo": "liverpool_fc"
    },
    {
        "rank": "6.",
        "name": "Alan Shearer",
        "country": "England",
        "team": "Newcastle United",
        "goals": "17",
        "flag": "england",
        "logo": "newcastle_united"
    },
    {
        "rank": "7.",
        "name": "Nicolas Anelka",
        "country": "France",
        "team": "Manchester City",
        "goals": "14",
        "flag": "france",
        "logo": "manchester_city"
    },
    {
        "rank": "-",
        "name": "Robbie Keane",
        "country": "Ireland",
        "team": "Leeds United",
        "goals": "14",
        "flag": "ireland",
        "logo": "leeds_united"
    },
    {
        "rank": "-",
        "name": "Harry Kewell",
        "country": "Australia",
        "team": "Leeds United",
        "goals": "14",
        "flag": "australia",
        "logo": "leeds_united"
    },
    {
        "rank": "-",
        "name": "Robert Pirés",
        "country": "France",
        "team": "Arsenal FC",
        "goals": "14",
        "flag": "france",
        "logo": "arsenal_fc"
    },
    {
        "rank": "-",
        "name": "Paul Scholes",
        "country": "England",
        "team": "Manchester United",
        "goals": "14",
        "flag": "england",
        "logo": "manchester_united"
    },
    {
        "rank": "-",
        "name": "Gianfranco Zola",
        "country": "Italy",
        "team": "Chelsea FC",
        "goals": "14",
        "flag": "italy",
        "logo": "chelsea_fc"
    },
    {
        "rank": "13.",
        "name": "Teddy Sheringham",
        "country": "England",
        "team": "Tottenham Hotspur",
        "goals": "12",
        "flag": "england",
        "logo": "tottenham_hotspur"
    },
    {
        "rank": "14.",
        "name": "Jimmy Floyd Hasselbaink",
        "country": "Netherlands",
        "team": "Chelsea FC",
        "goals": "11",
        "flag": "netherlands",
        "logo": "chelsea_fc"
    },
    {
        "rank": "-",
        "name": "Tomasz Radzinski",
        "country": "Canada",
        "team": "Everton FC",
        "goals": "11",
        "flag": "canada",
        "logo": "everton_fc"
    },
    {
        "rank": "16.",
        "name": "Kevin Campbell",
        "country": "England",
        "team": "Everton FC",
        "goals": "10",
        "flag": "england",
        "logo": "everton_fc"
    },
    {
        "rank": "-",
        "name": "Dion Dublin",
        "country": "England",
        "team": "Aston Villa",
        "goals": "10",
        "flag": "england",
        "logo": "aston_villa"
    },
    {
        "rank": "-",
        "name": "Jason Euell",
        "country": "Jamaica",
        "team": "Charlton Athletic",
        "goals": "10",
        "flag": "jamaica",
        "logo": "charlton_athletic"
    },
    {
        "rank": "-",
        "name": "Eiður Guðjohnsen",
        "country": "Iceland",
        "team": "Chelsea FC",
        "goals": "10",
        "flag": "iceland",
        "logo": "chelsea_fc"
    },
    {
        "rank": "-",
        "name": "Sylvain Wiltord",
        "country": "France",
        "team": "Arsenal FC",
        "goals": "10",
        "flag": "france",
        "logo": "arsenal_fc"
    }
]