[
    {
        "rank": "1",
        "team": "Real Madrid",
        "points": "24",
        "played": "10",
        "win": "7",
        "draw": "3",
        "lost": "0",
        "goalsFor": "28",
        "goalsAgainst": "10",
        "goalDifference": "18",
        "logo": "real_madrid"
    },
    {
        "rank": "2",
        "team": "Sevilla FC",
        "points": "21",
        "played": "10",
        "win": "6",
        "draw": "3",
        "lost": "1",
        "goalsFor": "18",
        "goalsAgainst": "13",
        "goalDifference": "5",
        "logo": "sevilla_fc"
    },
    {
        "rank": "3",
        "team": "FC Barcelona",
        "points": "19",
        "played": "9",
        "win": "6",
        "draw": "1",
        "lost": "2",
        "goalsFor": "29",
        "goalsAgainst": "12",
        "goalDifference": "17",
        "logo": "fc_barcelona"
    },
    {
        "rank": "4",
        "team": "Villarreal CF",
        "points": "19",
        "played": "9",
        "win": "5",
        "draw": "4",
        "lost": "0",
        "goalsFor": "16",
        "goalsAgainst": "5",
        "goalDifference": "11",
        "logo": "villarreal_cf"
    },
    {
        "rank": "5",
        "team": "Atlético Madrid",
        "points": "18",
        "played": "9",
        "win": "5",
        "draw": "3",
        "lost": "1",
        "goalsFor": "21",
        "goalsAgainst": "4",
        "goalDifference": "17",
        "logo": "atletico_madrid"
    },
    {
        "rank": "6",
        "team": "Real Sociedad",
        "points": "16",
        "played": "10",
        "win": "5",
        "draw": "1",
        "lost": "4",
        "goalsFor": "16",
        "goalsAgainst": "12",
        "goalDifference": "4",
        "logo": "real_sociedad"
    },
    {
        "rank": "7",
        "team": "Athletic Bilbao",
        "points": "15",
        "played": "9",
        "win": "5",
        "draw": "0",
        "lost": "4",
        "goalsFor": "14",
        "goalsAgainst": "12",
        "goalDifference": "2",
        "logo": "athletic_bilbao"
    },
    {
        "rank": "8",
        "team": "Celta Vigo",
        "points": "13",
        "played": "9",
        "win": "4",
        "draw": "1",
        "lost": "4",
        "goalsFor": "13",
        "goalsAgainst": "17",
        "goalDifference": "-4",
        "logo": "celta_vigo"
    },
    {
        "rank": "9",
        "team": "UD Las Palmas",
        "points": "12",
        "played": "9",
        "win": "3",
        "draw": "3",
        "lost": "3",
        "goalsFor": "17",
        "goalsAgainst": "15",
        "goalDifference": "2",
        "logo": "ud_las_palmas"
    },
    {
        "rank": "10",
        "team": "Málaga CF",
        "points": "12",
        "played": "9",
        "win": "3",
        "draw": "3",
        "lost": "3",
        "goalsFor": "12",
        "goalsAgainst": "10",
        "goalDifference": "2",
        "logo": "malaga_cf"
    },
    {
        "rank": "11",
        "team": "SD Eibar",
        "points": "12",
        "played": "9",
        "win": "3",
        "draw": "3",
        "lost": "3",
        "goalsFor": "14",
        "goalsAgainst": "13",
        "goalDifference": "1",
        "logo": "sd_eibar"
    },
    {
        "rank": "12",
        "team": "Real Betis",
        "points": "11",
        "played": "9",
        "win": "3",
        "draw": "2",
        "lost": "4",
        "goalsFor": "11",
        "goalsAgainst": "19",
        "goalDifference": "-8",
        "logo": "real_betis"
    },
    {
        "rank": "13",
        "team": "CD Alavés",
        "points": "10",
        "played": "10",
        "win": "2",
        "draw": "4",
        "lost": "4",
        "goalsFor": "10",
        "goalsAgainst": "15",
        "goalDifference": "-5",
        "logo": "cd_alaves"
    },
    {
        "rank": "14",
        "team": "CD Leganés",
        "points": "10",
        "played": "10",
        "win": "3",
        "draw": "1",
        "lost": "6",
        "goalsFor": "9",
        "goalsAgainst": "19",
        "goalDifference": "-10",
        "logo": "cd_leganes"
    },
    {
        "rank": "15",
        "team": "Valencia CF",
        "points": "9",
        "played": "9",
        "win": "3",
        "draw": "0",
        "lost": "6",
        "goalsFor": "13",
        "goalsAgainst": "18",
        "goalDifference": "-5",
        "logo": "valencia_cf"
    },
    {
        "rank": "16",
        "team": "Sporting Gijón",
        "points": "9",
        "played": "10",
        "win": "2",
        "draw": "3",
        "lost": "5",
        "goalsFor": "8",
        "goalsAgainst": "19",
        "goalDifference": "-11",
        "logo": "sporting_gijon"
    },
    {
        "rank": "17",
        "team": "Espanyol Barcelona",
        "points": "8",
        "played": "9",
        "win": "1",
        "draw": "5",
        "lost": "3",
        "goalsFor": "12",
        "goalsAgainst": "17",
        "goalDifference": "-5",
        "logo": "espanyol_barcelona"
    },
    {
        "rank": "18",
        "team": "Deportivo La Coruña",
        "points": "8",
        "played": "9",
        "win": "2",
        "draw": "2",
        "lost": "5",
        "goalsFor": "6",
        "goalsAgainst": "14",
        "goalDifference": "-8",
        "logo": "deportivo_la_coruna"
    },
    {
        "rank": "19",
        "team": "CA Osasuna",
        "points": "6",
        "played": "9",
        "win": "1",
        "draw": "3",
        "lost": "5",
        "goalsFor": "11",
        "goalsAgainst": "19",
        "goalDifference": "-8",
        "logo": "ca_osasuna"
    },
    {
        "rank": "20",
        "team": "Granada CF",
        "points": "3",
        "played": "9",
        "win": "0",
        "draw": "3",
        "lost": "6",
        "goalsFor": "8",
        "goalsAgainst": "23",
        "goalDifference": "-15",
        "logo": "granada_cf"
    }
]